horde_safety/__init__.py
horde_safety/_version.py
horde_safety/csam_checker.py
horde_safety/deep_danbooru_model.py
horde_safety/interrogate.py
horde_safety/nsfw_checker_class.py
horde_safety/py.typed
horde_safety/utils.py
horde_safety-0.3.0.dist-info/licenses/LICENSE
horde_safety-0.3.0.dist-info/METADATA
horde_safety-0.3.0.dist-info/WHEEL
horde_safety-0.3.0.dist-info/top_level.txt
horde_safety-0.3.0.dist-info/RECORD
