Metadata-Version: 2.4
Name: horde_safety
Version: 0.3.0
Summary: Provides some of the tools the AI Horde uses for safety.
Author-email: db0 <mail@dbzer0.com>, tazlin <tazlin.on.github@gmail.com>
License: GNU AFFERO GENERAL PUBLIC LICENSE
Project-URL: Homepage, https://github.com/Haidra-Org/horde-safety/
Project-URL: Bug Tracker, https://github.com/Haidra-Org/horde-safety/issues
Classifier: Programming Language :: Python :: 3
Classifier: License :: OSI Approved :: GNU Affero General Public License v3
Classifier: Operating System :: OS Independent
Classifier: Development Status :: 4 - Beta
Requires-Python: >=3.10
License-File: LICENSE
Requires-Dist: torch
Requires-Dist: clip-interrogator==0.6.0
Requires-Dist: unidecode
Requires-Dist: loguru
Requires-Dist: strenum
Requires-Dist: pillow
Requires-Dist: python-dotenv
Requires-Dist: pydantic
Dynamic: license-file
